packages/__init__.py
packages/thomastestpackage.py
thomas_test_library-0.0.2.dist-info/LICENSE
thomas_test_library-0.0.2.dist-info/METADATA
thomas_test_library-0.0.2.dist-info/WHEEL
thomas_test_library-0.0.2.dist-info/top_level.txt
thomas_test_library-0.0.2.dist-info/RECORD
