Metadata-Version: 2.1
Name: thomas-test-library
Version: 0.0.2
Summary: First test
Home-page: https://github.com/pypa/sampleproject
Author: Thomas Steiner
Author-email: thomas.a.steiner@bilfinger.com
License: UNKNOWN
Platform: UNKNOWN
Classifier: Programming Language :: Python :: 3
Classifier: License :: OSI Approved :: MIT License
Classifier: Operating System :: OS Independent
License-File: LICENSE
